betteruptime/__init__.py
betteruptime/typing.py
betteruptime/version.py
betteruptime/api/__init__.py
betteruptime/api/api_client.py
betteruptime/api/exceptions.py
betteruptime/api/http_client.py
betteruptime/resources/__init__.py
betteruptime/resources/abstract.py
betteruptime/resources/escalation_policies.py
betteruptime/resources/generic.py
betteruptime/resources/heartbeat_groups.py
betteruptime/resources/heartbeats.py
betteruptime/resources/incidents.py
betteruptime/resources/metadata.py
betteruptime/resources/monitor_groups.py
betteruptime/resources/monitors.py
betteruptime/resources/on_call_calendar.py
betteruptime/resources/status_pages/__init__.py
betteruptime/resources/status_pages/reports.py
betteruptime/resources/status_pages/resources.py
betteruptime/resources/status_pages/sections.py
betteruptime/resources/status_pages/status_pages.py
betteruptime/resources/status_pages/status_updates.py
betteruptime/util/__init__.py
betteruptime/util/errors.py
betteruptime/util/format.py
tests/__init__.py
tests/test_client.py
betteruptime-0.1.6.dist-info/LICENSE
betteruptime-0.1.6.dist-info/METADATA
betteruptime-0.1.6.dist-info/WHEEL
betteruptime-0.1.6.dist-info/top_level.txt
betteruptime-0.1.6.dist-info/zip-safe
betteruptime-0.1.6.dist-info/RECORD
